django_settings_file/__init__.py
django_settings_file/py.typed
django_settings_file/settings.py
django_settings_file-2.10.1.dist-info/LICENSE
django_settings_file-2.10.1.dist-info/METADATA
django_settings_file-2.10.1.dist-info/WHEEL
django_settings_file-2.10.1.dist-info/top_level.txt
django_settings_file-2.10.1.dist-info/RECORD
