Metadata-Version: 2.1
Name: django-settings-file
Version: 2.10.1
Summary: Let Django use settings from an arbitrary Python file instead of an importable module
Home-page: https://github.com/adamchainz/django-settings-file
Author: Adam Johnson
Author-email: me@adamj.eu
License: MIT
Project-URL: Changelog, https://github.com/adamchainz/django-settings-file/blob/main/HISTORY.rst
Project-URL: Twitter, https://twitter.com/adamchainz
Keywords: Django
Classifier: Development Status :: 7 - Inactive
Classifier: Framework :: Django :: 3.2
Classifier: Framework :: Django :: 4.0
Classifier: Framework :: Django :: 4.1
Classifier: Intended Audience :: Developers
Classifier: License :: OSI Approved :: MIT License
Classifier: Natural Language :: English
Classifier: Operating System :: OS Independent
Classifier: Programming Language :: Python :: 3 :: Only
Classifier: Programming Language :: Python :: 3
Classifier: Programming Language :: Python :: 3.7
Classifier: Programming Language :: Python :: 3.8
Classifier: Programming Language :: Python :: 3.9
Classifier: Programming Language :: Python :: 3.10
Classifier: Programming Language :: Python :: 3.11
Classifier: Typing :: Typed
Requires-Python: >=3.7
License-File: LICENSE
Requires-Dist: Django (>=3.2)
